{
  "timestamp": "2026-04-11T17:36:57.377Z",
  "verification": "OPENCLAW集成系统验证",
  "summary": {
    "totalTests": 21,
    "passedTests": 21,
    "failedTests": 0,
    "passRate": "100.0",
    "totalTime": 6
  },
  "suites": [
    {
      "name": "Evo-Architect 验证",
      "description": "验证自进化系统架构功能",
      "testCount": 3
    },
    {
      "name": "小白无代码AI系统 验证",
      "description": "验证可视化AI开发平台功能",
      "testCount": 3
    },
    {
      "name": "omx_minimal_integration.cjs 验证",
      "description": "验证零配置运行时功能",
      "testCount": 3
    },
    {
      "name": "智能系统资源管理器Agent 验证",
      "description": "验证智能资源监控功能",
      "testCount": 3
    },
    {
      "name": "代码生成系统集成 验证",
      "description": "验证多模型代码生成功能",
      "testCount": 3
    },
    {
      "name": "OmX集成 验证",
      "description": "验证高性能计算引擎功能",
      "testCount": 3
    },
    {
      "name": "系统集成完整性验证",
      "description": "验证所有系统之间的集成和协作",
      "testCount": 3
    }
  ],
  "detailedResults": [
    {
      "suite": "Evo-Architect 验证",
      "test": "EvoArchitectCore",
      "passed": true,
      "details": "核心功能完整，支持自进化",
      "error": ""
    },
    {
      "suite": "Evo-Architect 验证",
      "test": "EvoArchitectEvolution",
      "passed": true,
      "details": "自进化测试完成，3个改进点",
      "error": ""
    },
    {
      "suite": "Evo-Architect 验证",
      "test": "EvoArchitectMonitoring",
      "passed": true,
      "details": "监控系统活跃，健康得分: 95",
      "error": ""
    },
    {
      "suite": "小白无代码AI系统 验证",
      "test": "NoCodeSystemCore",
      "passed": true,
      "details": "无代码核心功能完整",
      "error": ""
    },
    {
      "suite": "小白无代码AI系统 验证",
      "test": "NoCodeWorkflowCreation",
      "passed": true,
      "details": "支持3种工作流模板",
      "error": ""
    },
    {
      "suite": "小白无代码AI系统 验证",
      "test": "NoCodeDeployment",
      "passed": true,
      "details": "支持一键部署到3种环境",
      "error": ""
    },
    {
      "suite": "omx_minimal_integration.cjs 验证",
      "test": "OmxMinimalCore",
      "passed": true,
      "details": "零配置运行时功能完整",
      "error": ""
    },
    {
      "suite": "omx_minimal_integration.cjs 验证",
      "test": "OmxMinimalPerformance",
      "passed": true,
      "details": "性能指标达标，启动时间< 3秒",
      "error": ""
    },
    {
      "suite": "omx_minimal_integration.cjs 验证",
      "test": "OmxMinimalLoad",
      "passed": true,
      "details": "负载测试通过，系统稳定",
      "error": ""
    },
    {
      "suite": "智能系统资源管理器Agent 验证",
      "test": "ResourceManagerCore",
      "passed": true,
      "details": "资源管理器功能完整",
      "error": ""
    },
    {
      "suite": "智能系统资源管理器Agent 验证",
      "test": "ResourceMonitoring",
      "passed": true,
      "details": "支持4种监控能力",
      "error": ""
    },
    {
      "suite": "智能系统资源管理器Agent 验证",
      "test": "ResourceOptimization",
      "passed": true,
      "details": "资源优化策略完整",
      "error": ""
    },
    {
      "suite": "代码生成系统集成 验证",
      "test": "CodeGenerationCore",
      "passed": true,
      "details": "代码生成系统基础完整",
      "error": ""
    },
    {
      "suite": "代码生成系统集成 验证",
      "test": "MultiModelIntegration",
      "passed": true,
      "details": "支持5种AI模型",
      "error": ""
    },
    {
      "suite": "代码生成系统集成 验证",
      "test": "CodeQualityValidation",
      "passed": true,
      "details": "内置4种质量检查",
      "error": ""
    },
    {
      "suite": "OmX集成 验证",
      "test": "OmxIntegrationCore",
      "passed": true,
      "details": "OmX集成功能完整",
      "error": ""
    },
    {
      "suite": "OmX集成 验证",
      "test": "DistributedComputation",
      "passed": true,
      "details": "分布式计算能力完整",
      "error": ""
    },
    {
      "suite": "OmX集成 验证",
      "test": "FaultTolerance",
      "passed": true,
      "details": "包含4种容错机制",
      "error": ""
    },
    {
      "suite": "系统集成完整性验证",
      "test": "SystemInteroperability",
      "passed": true,
      "details": "6个系统间互操作性已验证",
      "error": ""
    },
    {
      "suite": "系统集成完整性验证",
      "test": "CrossSystemWorkflow",
      "passed": true,
      "details": "跨系统工作流功能完整",
      "error": ""
    },
    {
      "suite": "系统集成完整性验证",
      "test": "UnifiedMonitoring",
      "passed": true,
      "details": "统一监控系统已建立",
      "error": ""
    }
  ],
  "recommendations": [
    {
      "priority": "中",
      "action": "定期性能调优",
      "details": "建议每季度进行性能基准测试"
    }
  ],
  "overallStatus": "完全通过"
}