{
  "round": 7,
  "topic": "浏览器自动化低负载实现",
  "category": "S7",
  "timestamp": "2026-04-13T07:55:00.503Z",
  "implementationType": "低负载浏览器自动化",
  "implementationApproach": "无头浏览器 + 智能调度",
  "resourceRequirements": {
    "memory": "256MB",
    "cpu": "0.3核",
    "disk": "1GB"
  },
  "existingSolutions": [
    "Puppeteer轻量版",
    "Selenium精简",
    "自定义驱动"
  ],
  "feasibilityScore": 91,
  "recommendedTools": [
    "Puppeteer",
    "Selenium",
    "浏览器驱动"
  ],
  "implementationPriority": "高优先级 - 立即实施"
}